asymysql.py
asymysql-1.4.0.4.dist-info/LICENSE
asymysql-1.4.0.4.dist-info/WHEEL
asymysql-1.4.0.4.dist-info/METADATA
asymysql-1.4.0.4.dist-info/RECORD
