Metadata-Version: 2.1
Name: asymysql
Version: 1.4.0.4
Summary: 异步的 mysql ORM
Keywords: coolmysql,asymysql,pymysql,mysql,aiomysql,orm
Author-email: "lcctoor.com" <lcctoor@outlook.com>
Classifier: License :: OSI Approved :: Apache Software License
Requires-Dist: arts>=2023.11.26
Project-URL: HomePage, https://github.com/lcctoor/arts/tree/main/arts/asymysql
